MANIFEST.in
README.txt
setup.cfg
setup.py
docs/HISTORY.txt
docs/INSTALL.txt
docs/LICENSE.GPL
docs/LICENSE.txt
enpraxis/__init__.py
enpraxis.leftskin.egg-info/PKG-INFO
enpraxis.leftskin.egg-info/SOURCES.txt
enpraxis.leftskin.egg-info/dependency_links.txt
enpraxis.leftskin.egg-info/entry_points.txt
enpraxis.leftskin.egg-info/namespace_packages.txt
enpraxis.leftskin.egg-info/not-zip-safe
enpraxis.leftskin.egg-info/requires.txt
enpraxis.leftskin.egg-info/top_level.txt
enpraxis/leftskin/__init__.py
enpraxis/leftskin/config.py
enpraxis/leftskin/configure.zcml
enpraxis/leftskin/overrides.zcml
enpraxis/leftskin/setupHandlers.py
enpraxis/leftskin/version.txt
enpraxis/leftskin/browser/__init__.py
enpraxis/leftskin/browser/configure.zcml
enpraxis/leftskin/browser/controlpanel.py
enpraxis/leftskin/browser/controlpaneladv.py
enpraxis/leftskin/browser/controlpanelcompl.py
enpraxis/leftskin/browser/interfaces.py
enpraxis/leftskin/browser/leftskinview.py
enpraxis/leftskin/browser/personal_roles_bar.pt
enpraxis/leftskin/browser/schema.py
enpraxis/leftskin/browser/skin.gif
enpraxis/leftskin/browser/skins.py
enpraxis/leftskin/browser/viewlets.py
enpraxis/leftskin/browser/widgets.py
enpraxis/leftskin/docs/about.html
enpraxis/leftskin/docs/web.css
enpraxis/leftskin/docs/images/install_leftskin.png
enpraxis/leftskin/docs/images/leftskin_colorpicker.png
enpraxis/leftskin/docs/images/leftskin_colorwheel.png
enpraxis/leftskin/docs/images/leftskin_helper.png
enpraxis/leftskin/docs/images/leftskincss_categories.png
enpraxis/leftskin/docs/images/leftskincss_settings.png
enpraxis/leftskin/docs/src/ABOUT.rst
enpraxis/leftskin/locales/leftskin.pot
enpraxis/leftskin/locales/af/LC_MESSAGES/leftskin.po
enpraxis/leftskin/locales/ar/LC_MESSAGES/leftskin.po
enpraxis/leftskin/locales/bn/LC_MESSAGES/leftskin.po
enpraxis/leftskin/locales/ca/LC_MESSAGES/leftskin.po
enpraxis/leftskin/locales/de/LC_MESSAGES/leftskin.po
enpraxis/leftskin/locales/en/LC_MESSAGES/leftskin.po
enpraxis/leftskin/locales/es/LC_MESSAGES/leftskin.mo
enpraxis/leftskin/locales/es/LC_MESSAGES/leftskin.po
enpraxis/leftskin/locales/fr/LC_MESSAGES/leftskin.po
enpraxis/leftskin/locales/hi/LC_MESSAGES/leftskin.po
enpraxis/leftskin/locales/hu/LC_MESSAGES/leftskin.po
enpraxis/leftskin/locales/it/LC_MESSAGES/leftskin.po
enpraxis/leftskin/locales/ja/LC_MESSAGES/leftskin.po
