Metadata-Version: 1.1
Name: enpraxis.leftskin
Version: 2.5
Summary: Leftskin is a skin product for Plone that customizes the look of your Plone site, adding a left hand column for navigation.
Home-page: http://svn.enpraxis.net/svn/enpraxis.leftskin/trunk
Author: display. It allows the left column to be styled, and retains the ablilty to move
Author-email: portlets into and out of it with no additional styling required.
License: GPL
Keywords: skin leftskin Plone
Platform: UNKNOWN
Classifier: Framework :: Plone
Classifier: Programming Language :: Python
Classifier: Topic :: Software Development :: Libraries :: Python Modules
